cipromote/__init__.py
cipromote/awx.py
cipromote/ci-cli.py
cipromote/ci-cli.py_v1
cipromote/cli.py
cipromote/constants.py
cipromote/deployment.py
cipromote/example_cli/example_v3.4.5/README.md
cipromote/example_cli/example_v3.4.5/ci-cli.py
cipromote/example_cli/example_v3.4.5/constants.py
cipromote/example_cli/example_v3.4.5/instances.py
cipromote/example_cli/example_v3.4.5/label_versions.py
cipromote/example_cli/example_v3.4.5/labels.py
cipromote/example_cli/example_v3.4.5/login.py
cipromote/example_cli/example_v3.4.5/loginInput.py
cipromote/example_cli/example_v3.4.5/projects.py
cipromote/example_cli/example_v3.4.5/queries.py
cipromote/example_cli/example_v3.4.5/requirements.txt
cipromote/example_cli/example_v3.4.5/versioned_items.py
cipromote/instances.py
cipromote/instances.py_v1
cipromote/label_versions.py
cipromote/label_versions.py_v1
cipromote/labels.py
cipromote/login.py
cipromote/loginInput.py
cipromote/motio-original-src-2025/README.md
cipromote/motio-original-src-2025/ci-cli.py
cipromote/motio-original-src-2025/constants.py
cipromote/motio-original-src-2025/deployment.py
cipromote/motio-original-src-2025/instances.py
cipromote/motio-original-src-2025/label_versions.py
cipromote/motio-original-src-2025/labels.py
cipromote/motio-original-src-2025/login.py
cipromote/motio-original-src-2025/loginInput.py
cipromote/motio-original-src-2025/projects.py
cipromote/motio-original-src-2025/queries.py
cipromote/motio-original-src-2025/requirements.txt
cipromote/motio-original-src-2025/versioned_items.py
cipromote/projects.py
cipromote/queries.py
cipromote/queries.py_v1
cipromote/versioned_items.py
cipromote-2.0.1.dist-info/METADATA
cipromote-2.0.1.dist-info/WHEEL
cipromote-2.0.1.dist-info/entry_points.txt
cipromote-2.0.1.dist-info/RECORD
